{
  "annotations": {
    "list": [
      {
        "builtIn": 1,
        "datasource": "-- Grafana --",
        "enable": true,
        "hide": true,
        "iconColor": "rgba(0, 211, 255, 1)",
        "name": "Annotations & Alerts",
        "type": "dashboard"
      }
    ]
  },
  "editable": true,
  "gnetId": null,
  "graphTooltip": 1,
  "id": null,
  "links": [],
  "panels": [
    {
      "collapsed": false,
      "gridPos": {
        "h": 1,
        "w": 24,
        "x": 0,
        "y": 0
      },
      "id": 100,
      "title": "Shift Overview",
      "type": "row"
    },
    {
      "datasource": "InfluxDB",
      "fieldConfig": {
        "defaults": {
          "thresholds": {
            "mode": "absolute",
            "steps": [
              {
                "color": "green",
                "value": null
              }
            ]
          },
          "unit": "short"
        }
      },
      "gridPos": {
        "h": 5,
        "w": 6,
        "x": 0,
        "y": 1
      },
      "id": 1,
      "options": {
        "colorMode": "value",
        "graphMode": "none",
        "orientation": "auto",
        "reduceOptions": {
          "calcs": [
            "lastNotNull"
          ],
          "fields": "",
          "values": false
        },
        "textMode": "auto"
      },
      "targets": [
        {
          "query": "from(bucket: \"manufacturing\")\n  |> range(start: v.timeRangeStart, stop: v.timeRangeStop)\n  |> filter(fn: (r) => r._measurement == \"sim_events\")\n  |> filter(fn: (r) => r.run_id =~ /^${run_id}$/)\n  |> filter(fn: (r) => r.event_type == \"SHIFT_CHANGE\")\n  |> filter(fn: (r) => r._field == \"sim_time\")\n  |> count()"
        }
      ],
      "title": "Total Shift Changes",
      "type": "stat"
    },
    {
      "datasource": "InfluxDB",
      "fieldConfig": {
        "defaults": {
          "thresholds": {
            "mode": "absolute",
            "steps": [
              {
                "color": "blue",
                "value": null
              }
            ]
          },
          "unit": "none"
        }
      },
      "gridPos": {
        "h": 5,
        "w": 6,
        "x": 6,
        "y": 1
      },
      "id": 2,
      "options": {
        "colorMode": "value",
        "graphMode": "none",
        "orientation": "auto",
        "reduceOptions": {
          "calcs": [
            "lastNotNull"
          ],
          "fields": "",
          "values": false
        },
        "textMode": "auto"
      },
      "targets": [
        {
          "query": "from(bucket: \"manufacturing\")\n  |> range(start: v.timeRangeStart, stop: v.timeRangeStop)\n  |> filter(fn: (r) => r._measurement == \"opcua\")\n  |> filter(fn: (r) => r.run_id =~ /^${run_id}$/)\n  |> filter(fn: (r) => r._field == \"Shift_Name\")\n  |> last()"
        }
      ],
      "title": "Current Shift",
      "type": "stat"
    },
    {
      "datasource": "InfluxDB",
      "fieldConfig": {
        "defaults": {
          "thresholds": {
            "mode": "absolute",
            "steps": [
              {
                "color": "green",
                "value": null
              }
            ]
          },
          "unit": "short"
        }
      },
      "gridPos": {
        "h": 5,
        "w": 6,
        "x": 12,
        "y": 1
      },
      "id": 3,
      "options": {
        "colorMode": "value",
        "graphMode": "area",
        "orientation": "auto",
        "reduceOptions": {
          "calcs": [
            "lastNotNull"
          ],
          "fields": "",
          "values": false
        },
        "textMode": "auto"
      },
      "targets": [
        {
          "query": "from(bucket: \"manufacturing\")\n  |> range(start: v.timeRangeStart, stop: v.timeRangeStop)\n  |> filter(fn: (r) => r._measurement == \"opcua\")\n  |> filter(fn: (r) => r.run_id =~ /^${run_id}$/)\n  |> filter(fn: (r) => r._field == \"ShiftTotal_Parts\")\n  |> last()"
        }
      ],
      "title": "Total Parts (All Shifts)",
      "type": "stat"
    },
    {
      "datasource": "InfluxDB",
      "fieldConfig": {
        "defaults": {
          "thresholds": {
            "mode": "absolute",
            "steps": [
              {
                "color": "red",
                "value": null
              },
              {
                "color": "yellow",
                "value": 50
              },
              {
                "color": "green",
                "value": 80
              }
            ]
          },
          "unit": "percent"
        }
      },
      "gridPos": {
        "h": 5,
        "w": 6,
        "x": 18,
        "y": 1
      },
      "id": 10,
      "options": {
        "colorMode": "value",
        "graphMode": "area",
        "orientation": "auto",
        "reduceOptions": {
          "calcs": [
            "lastNotNull"
          ],
          "fields": "",
          "values": false
        },
        "textMode": "auto"
      },
      "targets": [
        {
          "query": "from(bucket: \"manufacturing\")\n  |> range(start: v.timeRangeStart, stop: v.timeRangeStop)\n  |> filter(fn: (r) => r._measurement == \"opcua\")\n  |> filter(fn: (r) => r.run_id =~ /^${run_id}$/)\n  |> filter(fn: (r) => r._field == \"CurrShift_OEE\")\n  |> last()\n  |> map(fn: (r) => ({r with _value: r._value * 100.0}))"
        }
      ],
      "title": "Current Shift OEE",
      "type": "stat"
    },
    {
      "collapsed": false,
      "gridPos": {
        "h": 1,
        "w": 24,
        "x": 0,
        "y": 6
      },
      "id": 101,
      "title": "Shift Production",
      "type": "row"
    },
    {
      "datasource": "InfluxDB",
      "description": "Parts produced in current shift over time",
      "fieldConfig": {
        "defaults": {
          "custom": {
            "drawStyle": "line",
            "lineInterpolation": "linear",
            "fillOpacity": 10
          },
          "unit": "short"
        }
      },
      "gridPos": {
        "h": 8,
        "w": 12,
        "x": 0,
        "y": 7
      },
      "id": 4,
      "targets": [
        {
          "query": "from(bucket: \"manufacturing\")\n  |> range(start: v.timeRangeStart, stop: v.timeRangeStop)\n  |> filter(fn: (r) => r._measurement == \"opcua\")\n  |> filter(fn: (r) => r.run_id =~ /^${run_id}$/)\n  |> filter(fn: (r) => r._field == \"CurrShift_Parts\")\n  |> aggregateWindow(every: v.windowPeriod, fn: last, createEmpty: false)"
        }
      ],
      "title": "Current Shift Parts Over Time",
      "type": "timeseries"
    },
    {
      "datasource": "InfluxDB",
      "description": "Cumulative production across all shifts",
      "fieldConfig": {
        "defaults": {
          "custom": {
            "drawStyle": "line",
            "lineInterpolation": "linear",
            "fillOpacity": 10
          },
          "unit": "short"
        }
      },
      "gridPos": {
        "h": 8,
        "w": 12,
        "x": 12,
        "y": 7
      },
      "id": 6,
      "targets": [
        {
          "query": "from(bucket: \"manufacturing\")\n  |> range(start: v.timeRangeStart, stop: v.timeRangeStop)\n  |> filter(fn: (r) => r._measurement == \"opcua\")\n  |> filter(fn: (r) => r.run_id =~ /^${run_id}$/)\n  |> filter(fn: (r) => r._field == \"Throughput\")\n  |> aggregateWindow(every: v.windowPeriod, fn: last, createEmpty: false)"
        }
      ],
      "title": "Cumulative Production",
      "type": "timeseries"
    },
    {
      "collapsed": false,
      "gridPos": {
        "h": 1,
        "w": 24,
        "x": 0,
        "y": 15
      },
      "id": 102,
      "title": "Shift Event Log",
      "type": "row"
    },
    {
      "datasource": "InfluxDB",
      "fieldConfig": {
        "defaults": {
          "custom": {
            "filterable": true
          }
        }
      },
      "gridPos": {
        "h": 8,
        "w": 24,
        "x": 0,
        "y": 16
      },
      "id": 7,
      "options": {
        "showHeader": true,
        "sortBy": [
          {
            "desc": true,
            "displayName": "Time"
          }
        ]
      },
      "targets": [
        {
          "query": "from(bucket: \"manufacturing\")\n  |> range(start: v.timeRangeStart, stop: v.timeRangeStop)\n  |> filter(fn: (r) => r._measurement == \"sim_events\")\n  |> filter(fn: (r) => r.run_id =~ /^${run_id}$/)\n  |> filter(fn: (r) => r.event_type == \"SHIFT_CHANGE\")\n  |> filter(fn: (r) => r._field == \"message\" or r._field == \"extra_json\")\n  |> pivot(rowKey: [\"_time\"], columnKey: [\"_field\"], valueColumn: \"_value\")\n  |> sort(columns: [\"_time\"], desc: true)"
        }
      ],
      "title": "Shift Change History",
      "type": "table"
    }
  ],
  "schemaVersion": 36,
  "style": "dark",
  "tags": [
    "manufacturing",
    "simantha",
    "shifts"
  ],
  "templating": {
    "list": [
      {
        "current": {
          "selected": true,
          "text": "All",
          "value": "$__all"
        },
        "datasource": "InfluxDB",
        "definition": "import \"influxdata/influxdb/schema\"\nschema.tagValues(bucket: \"manufacturing\", tag: \"run_id\")",
        "includeAll": true,
        "name": "run_id",
        "query": "import \"influxdata/influxdb/schema\"\nschema.tagValues(bucket: \"manufacturing\", tag: \"run_id\")",
        "refresh": 2,
        "type": "query",
        "allValue": ".*"
      }
    ]
  },
  "time": {
    "from": "now-1h",
    "to": "now"
  },
  "timepicker": {},
  "timezone": "browser",
  "title": "Shift Comparison",
  "uid": "simantha-shift-comparison",
  "version": 2
}